scripts/__init__.py
scripts/swrap_quicksetup.py
snakewrap/__init__.py
snakewrap/__version__.py
snakewrap/utils.py
snakewrap/wrapper.py
snakewrap/examples/__init__.py
snakewrap/examples/default_app.py
snakewrap/sample_manager/__init__.py
snakewrap/sample_manager/base.py
snakewrap/sample_manager/illumina_sample_manager.py
tests/__init__.py
tests/test_utils.py
tests/test_version.py
tests/test_wrapper.py
tests/sample_manager/__init__.py
tests/sample_manager/test_IlluminaSampleManager.py
tests/sample_manager/test_sample_manager.py
snakewrap-0.0.3.dist-info/LICENSE
snakewrap-0.0.3.dist-info/METADATA
snakewrap-0.0.3.dist-info/WHEEL
snakewrap-0.0.3.dist-info/entry_points.txt
snakewrap-0.0.3.dist-info/top_level.txt
snakewrap-0.0.3.dist-info/RECORD
