Metadata-Version: 2.1
Name: snakewrap
Version: 0.0.3
Summary: Snakemake Wrapper for NGS Pipelines
Home-page: UNKNOWN
Author: René Kmiecinski
Author-email: r.w.kmiecinski@gmail.com
License: GPL-v3
Platform: UNKNOWN
Classifier: Programming Language :: Python :: 3
Classifier: Programming Language :: Python :: 3.6
Classifier: Intended Audience :: Science/Research
Classifier: License :: OSI Approved :: GNU General Public License v3 (GPLv3)
Classifier: Topic :: Scientific/Engineering :: Bio-Informatics
Requires-Dist: snakemake (>5.26)
Requires-Dist: PyYAML
Requires-Dist: pandas
